{
  "timestamp_utc": "2025-Oct-20 06:19:29",
  "center": "Sun",
  "ref_plane": "ECLIPTIC",
  "units": {
    "distance": "au"
  },
  "bodies": [
    {
      "id": "199",
      "name": "Mercury",
      "type": "planet",
      "x": 0.1148341286621674,
      "y": -0.4362703783991908,
      "z": -0.0461855336506577
    },
    {
      "id": "299",
      "name": "Venus",
      "type": "planet",
      "x": -0.6763797840832466,
      "y": 0.240262922688683,
      "z": 0.0423278181400306
    },
    {
      "id": "399",
      "name": "Earth",
      "type": "planet",
      "x": 0.8891519154244186,
      "y": 0.4483998856436557,
      "z": -3.022374354533831e-05
    },
    {
      "id": "499",
      "name": "Mars",
      "type": "planet",
      "x": -0.6870827906474576,
      "y": -1.353382675168285,
      "z": -0.01151260853970417
    },
    {
      "id": "599",
      "name": "Jupiter",
      "type": "planet",
      "x": -1.159640084464364,
      "y": 5.054065523496093,
      "z": 0.004950861555942651
    },
    {
      "id": "699",
      "name": "Saturn",
      "type": "planet",
      "x": 9.532412173162083,
      "y": -0.1471499607476865,
      "z": -0.3768809857544089
    },
    {
      "id": "799",
      "name": "Uranus",
      "type": "planet",
      "x": 10.12848633834857,
      "y": 16.66653325729313,
      "z": -0.06943329422390643
    },
    {
      "id": "899",
      "name": "Neptune",
      "type": "planet",
      "x": 29.87719893811646,
      "y": 0.2892654744633097,
      "z": -0.6944521261053916
    }
  ],
  "failed": []
}