{
  "timestamp_utc": "2026-Mar-07 06:28:40",
  "center": "Sun",
  "ref_plane": "ECLIPTIC",
  "units": {
    "distance": "au"
  },
  "bodies": [
    {
      "id": "199",
      "name": "Mercury",
      "type": "planet",
      "x": -0.3545837544734025,
      "y": 0.0904515526191701,
      "z": 0.03991359431802192
    },
    {
      "id": "299",
      "name": "Venus",
      "type": "planet",
      "x": 0.6783180154234805,
      "y": 0.253642483063062,
      "z": -0.03565393532912677
    },
    {
      "id": "399",
      "name": "Earth",
      "type": "planet",
      "x": -0.9641553376395359,
      "y": 0.2345617277870117,
      "z": -6.360572373450125e-06
    },
    {
      "id": "499",
      "name": "Mars",
      "type": "planet",
      "x": 1.11955375819707,
      "y": -0.812231588236346,
      "z": -0.04447371692331935
    },
    {
      "id": "599",
      "name": "Jupiter",
      "type": "planet",
      "x": -2.157744253880967,
      "y": 4.770066143885709,
      "z": 0.0284613810593989
    },
    {
      "id": "699",
      "name": "Saturn",
      "type": "planet",
      "x": 9.47016158980786,
      "y": 0.6206495044964422,
      "z": -0.3877761472471612
    },
    {
      "id": "799",
      "name": "Uranus",
      "type": "planet",
      "x": 9.655837094889783,
      "y": 16.91671893283149,
      "z": -0.06237522503115437
    },
    {
      "id": "899",
      "name": "Neptune",
      "type": "planet",
      "x": 29.86607958490994,
      "y": 0.724970538752226,
      "z": -0.7031735197104884
    }
  ],
  "failed": []
}