{
  "timestamp_utc": "2026-Mar-13 06:40:45",
  "center": "Sun",
  "ref_plane": "ECLIPTIC",
  "units": {
    "distance": "au"
  },
  "bodies": [
    {
      "id": "199",
      "name": "Mercury",
      "type": "planet",
      "x": -0.3948564786612946,
      "y": -0.06998919253564012,
      "z": 0.03049561244845283
    },
    {
      "id": "299",
      "name": "Venus",
      "type": "planet",
      "x": 0.6260528162772643,
      "y": 0.3628539533767768,
      "z": -0.03113784047415408
    },
    {
      "id": "399",
      "name": "Earth",
      "type": "planet",
      "x": -0.9849975492044477,
      "y": 0.1326529646498704,
      "z": -2.438248902204989e-08
    },
    {
      "id": "499",
      "name": "Mars",
      "type": "planet",
      "x": 1.16983694631752,
      "y": -0.7353901418652107,
      "z": -0.04409640219469844
    },
    {
      "id": "599",
      "name": "Jupiter",
      "type": "planet",
      "x": -2.199536380741181,
      "y": 4.753307977171049,
      "z": 0.02946612513576898
    },
    {
      "id": "699",
      "name": "Saturn",
      "type": "planet",
      "x": 9.466042999378153,
      "y": 0.6540163922841203,
      "z": -0.3881933146843882
    },
    {
      "id": "799",
      "name": "Uranus",
      "type": "planet",
      "x": 9.635090323557518,
      "y": 16.92731526130693,
      "z": -0.06206639051899494
    },
    {
      "id": "899",
      "name": "Neptune",
      "type": "planet",
      "x": 29.86545297865287,
      "y": 0.7439326223208881,
      "z": -0.7035498042251139
    }
  ],
  "failed": []
}